LICENSE
MANIFEST.in
README.rst
setup.py
gruffy/__init__.py
gruffy/accumulator_bar.py
gruffy/area.py
gruffy/bar.py
gruffy/bar_conversion.py
gruffy/base.py
gruffy/bezier.py
gruffy/dot.py
gruffy/line.py
gruffy/pie.py
gruffy/sidebar.py
gruffy/stacked_area.py
gruffy/stacked_bar.py
gruffy/stacked_sidebar.py
gruffy.egg-info/PKG-INFO
gruffy.egg-info/SOURCES.txt
gruffy.egg-info/dependency_links.txt
gruffy.egg-info/not-zip-safe
gruffy.egg-info/requires.txt
gruffy.egg-info/top_level.txt
test/test_accumulator_bar.py
test/test_area.py
test/test_bar.py
test/test_base.py
test/test_bezier.py
test/test_dot.py
test/test_line.py
test/test_pie.py
test/test_sidebar.py
test/test_stacked_area.py
test/test_stacked_bar.py
test/test_stacked_sidebar.py