Metadata-Version: 1.1
Name: gruffy
Version: 0.3.4
Summary: Gruffy is Python implemetation of Gruff(Ruby Graphing Library)
Home-page: http://pypi.python.org/pypi/gruffy/
Author: Hideo Hattori
Author-email: hhatto.jp@gmail.com
License: MIT
Keywords: chart graph visualize
Platform: UNKNOWN
Classifier: Development Status :: 4 - Beta
Classifier: Operating System :: Unix
Classifier: License :: OSI Approved :: MIT License
Classifier: Programming Language :: Python
Classifier: Topic :: Multimedia :: Graphics
